{
  "parent_id": "138300",
  "reply_count": 2,
  "replies": [
    {
      "kind": "t1",
      "id": "1894291",
      "author": {
        "username": "Plenty-Entertainer10",
        "uid": null
      },
      "author_flair_text": null,
      "score": 2,
      "body": "<div class=\"wb-3\">您甭不服，咱北京的说唱奏是牛逼</div>",
      "replies": 0,
      "created": "22-06-08"
    },
    {
      "kind": "t1",
      "id": "1894408",
      "author": {
        "username": "SnooAdvice2604",
        "uid": null
      },
      "author_flair_text": null,
      "score": 1,
      "body": "<div class=\"wb-3\">北京晚报妞的屁股不够翘！想当明星的都得先被导演操！</div>",
      "replies": 0,
      "created": "22-06-08"
    }
  ]
}