{
  "parent_id": "138567",
  "reply_count": 2,
  "replies": [
    {
      "kind": "t1",
      "id": "1897400",
      "author": {
        "username": "KattleLaughter",
        "uid": null
      },
      "author_flair_text": null,
      "score": 5,
      "body": "<div class=\"wb-3\">一針見血 對匪系國家玩明白了 <br/>\n永遠不要跟匪類談判</div>",
      "replies": 0,
      "created": "22-06-09"
    },
    {
      "kind": "t1",
      "id": "1897764",
      "author": {
        "username": "kaneqc86",
        "uid": null
      },
      "author_flair_text": null,
      "score": 4,
      "body": "<div class=\"wb-3\">爱沙尼亚的“森林兄弟”在二战结束后通过游击战的方式抵抗苏联占领，最高峰时期达到了近三万人，而同时期爱沙尼亚全国人口不过一百万出头，大规模的战斗直到1953年才被KGB压制下去，而最后的反抗军则坚持到了1963年。</div>",
      "replies": 0,
      "created": "22-06-09"
    }
  ]
}