{
  "parent_id": "138615",
  "reply_count": 2,
  "replies": [
    {
      "kind": "t1",
      "id": "1898067",
      "author": {
        "username": "AdCreative8674",
        "uid": null
      },
      "author_flair_text": null,
      "score": 3,
      "body": "<div class=\"wb-3\">都讓你贏完了</div>",
      "replies": 0,
      "created": "22-06-10"
    },
    {
      "kind": "t1",
      "id": "1898061",
      "author": {
        "username": "reddishdish",
        "uid": null
      },
      "author_flair_text": null,
      "score": 3,
      "body": "<div class=\"wb-3\">收收味</div>",
      "replies": 0,
      "created": "22-06-10"
    }
  ]
}