{
  "parent_id": "139383",
  "reply_count": 2,
  "replies": [
    {
      "kind": "t1",
      "id": "1908769",
      "author": {
        "username": "Weierxunaidehua",
        "uid": null
      },
      "author_flair_text": null,
      "score": 10,
      "body": "<div class=\"wb-3\">好啊 就是你小子害我转学是吧</div>",
      "replies": 0,
      "created": "22-06-15"
    },
    {
      "kind": "t1",
      "id": "1908851",
      "author": {
        "username": "MilesGuoWengui",
        "uid": null
      },
      "author_flair_text": null,
      "score": 2,
      "body": "<div class=\"wb-3\">拷打一下周小平</div>",
      "replies": 0,
      "created": "22-06-15"
    }
  ]
}