{
  "parent_id": "139798",
  "reply_count": 8,
  "replies": [
    {
      "kind": "t1",
      "id": "1915259",
      "author": {
        "username": "[deleted]",
        "uid": null
      },
      "author_flair_text": null,
      "score": 2,
      "body": "<div class=\"wb-3\">笑嘻了，川剧变脸</div>",
      "replies": 0,
      "created": "22-06-19"
    },
    {
      "kind": "t1",
      "id": "1915403",
      "author": {
        "username": "[deleted]",
        "uid": null
      },
      "author_flair_text": null,
      "score": 1,
      "body": "<div class=\"wb-3\">洋大人都笑织女是巨婴</div>",
      "replies": 0,
      "created": "22-06-19"
    },
    {
      "kind": "t1",
      "id": "1915260",
      "author": {
        "username": "[deleted]",
        "uid": null
      },
      "author_flair_text": null,
      "score": 1,
      "body": "<div class=\"wb-3\">笑嘻了，川剧变脸</div>",
      "replies": 0,
      "created": "22-06-19"
    },
    {
      "kind": "t1",
      "id": "1915244",
      "author": {
        "username": "seafoodliyuanpeng",
        "uid": null
      },
      "author_flair_text": null,
      "score": 1,
      "body": "<div class=\"wb-3\">确实挺织的</div>",
      "replies": 0,
      "created": "22-06-19"
    },
    {
      "kind": "t1",
      "id": "1914974",
      "author": {
        "username": "[deleted]",
        "uid": null
      },
      "author_flair_text": null,
      "score": 1,
      "body": "<div class=\"wb-3\">什麼恐怖之森</div>",
      "replies": 0,
      "created": "22-06-19"
    },
    {
      "kind": "t1",
      "id": "1914959",
      "author": {
        "username": "[deleted]",
        "uid": null
      },
      "author_flair_text": null,
      "score": 1,
      "body": "<div class=\"wb-3\">打个nsfw</div>",
      "replies": 0,
      "created": "22-06-19"
    },
    {
      "kind": "t1",
      "id": "1914945",
      "author": {
        "username": "[deleted]",
        "uid": null
      },
      "author_flair_text": null,
      "score": 1,
      "body": "<div class=\"wb-3\">哭起來連五官都不太會動...</div>",
      "replies": 0,
      "created": "22-06-19"
    },
    {
      "kind": "t1",
      "id": "1914921",
      "author": {
        "username": "AmonOdins",
        "uid": null
      },
      "author_flair_text": null,
      "score": 1,
      "body": "<div class=\"wb-3\">笑了</div>",
      "replies": 0,
      "created": "22-06-19"
    }
  ]
}