{
  "parent_id": "139897",
  "reply_count": 3,
  "replies": [
    {
      "kind": "t1",
      "id": "1916198",
      "author": {
        "username": "[deleted]",
        "uid": null
      },
      "author_flair_text": null,
      "score": 18,
      "body": "<div class=\"wb-3\">什么蝙蝠侠视察下属</div>",
      "replies": 0,
      "created": "22-06-21"
    },
    {
      "kind": "t1",
      "id": "1916216",
      "author": {
        "username": "[deleted]",
        "uid": null
      },
      "author_flair_text": null,
      "score": 8,
      "body": "<div class=\"wb-3\">为什么拿佳得乐</div>",
      "replies": 0,
      "created": "22-06-21"
    },
    {
      "kind": "t1",
      "id": "1916451",
      "author": {
        "username": "[deleted]",
        "uid": null
      },
      "author_flair_text": null,
      "score": 3,
      "body": "<div class=\"wb-3\">在中国直接被民警拿下</div>",
      "replies": 0,
      "created": "22-06-21"
    }
  ]
}