{
  "parent_id": "1921377",
  "reply_count": 5,
  "replies": [
    {
      "kind": "t1",
      "id": "1921401",
      "author": {
        "username": "家得人体秤VS的",
        "uid": "92454"
      },
      "author_flair_text": "",
      "score": 6,
      "body": "<div class=\"wb-3\">我爷爷五岁的时候就被皇军开枪打死了</div>",
      "replies": 0,
      "created": "22-08-06"
    },
    {
      "kind": "t1",
      "id": "1921649",
      "author": {
        "username": "习大大的九个情人",
        "uid": "74485"
      },
      "author_flair_text": "为全球一亿多人达成净零排放目标的进步左派",
      "score": 3,
      "body": "<div class=\"wb-3\">你死的那天都不会解放，早点下去陪毛腊肉吧</div>",
      "replies": 0,
      "created": "22-08-08"
    },
    {
      "kind": "t1",
      "id": "1921405",
      "author": {
        "username": "平子给我挺住",
        "uid": "90392"
      },
      "author_flair_text": "他真的我哭死😭",
      "score": 3,
      "body": "<div class=\"wb-3\">我呼吸机呢？</div>",
      "replies": 0,
      "created": "22-08-06"
    },
    {
      "kind": "t1",
      "id": "1921842",
      "author": {
        "username": "shirami",
        "uid": "93072"
      },
      "author_flair_text": "",
      "score": 2,
      "body": "<div class=\"wb-3\">属于浪费医疗资源了，建议拔管</div>",
      "replies": 0,
      "created": "22-08-10"
    },
    {
      "kind": "t1",
      "id": "1921466",
      "author": {
        "username": "dogg0五入拖拉曼",
        "uid": "17555"
      },
      "author_flair_text": "中日韩都是支",
      "score": 1,
      "body": "<div class=\"wb-3\">农民</div>",
      "replies": 0,
      "created": "22-08-06"
    }
  ]
}