{
  "parent_id": "1921973",
  "reply_count": 2,
  "replies": [
    {
      "kind": "t1",
      "id": "1922073",
      "author": {
        "username": "家得人体秤VS的",
        "uid": "92454"
      },
      "author_flair_text": "",
      "score": 4,
      "body": "<div class=\"wb-3\">看镜头，茄子🍆</div>",
      "replies": 0,
      "created": "22-08-12"
    },
    {
      "kind": "t1",
      "id": "1921979",
      "author": {
        "username": "npccccccccc",
        "uid": "90611"
      },
      "author_flair_text": "吾心吾行澄如明镜,所发之帖全是偷的",
      "score": 3,
      "body": "<div class=\"wb-3\">有点哈人</div>",
      "replies": 0,
      "created": "22-08-12"
    }
  ]
}