{
  "parent_id": "1923394",
  "reply_count": 2,
  "replies": [
    {
      "kind": "t1",
      "id": "1923398",
      "author": {
        "username": "最爱国的希纳布塔",
        "uid": "92308"
      },
      "author_flair_text": "不要吃饭要核酸，不要自由要封控，不要尊严要谎言，不要改革要文革，不要选票要领袖，不做公民做奴才，喜迎圣主明君习近平。",
      "score": 3,
      "body": "<div class=\"wb-3\">安纳金是啥意思，是说手被欧比旺剁了吗<br/>\n这玩的什么怪梗</div>",
      "replies": 0,
      "created": "22-08-21"
    },
    {
      "kind": "t1",
      "id": "1923473",
      "author": {
        "username": "Fuk_Your_Allah",
        "uid": "23118"
      },
      "author_flair_text": "F.U.C.K your Allah",
      "score": 1,
      "body": "<div class=\"wb-3\">性别平等，多好啊</div>",
      "replies": 0,
      "created": "22-08-21"
    }
  ]
}