{
  "parent_id": "1924705",
  "reply_count": 5,
  "replies": [
    {
      "kind": "t1",
      "id": "1932523",
      "author": {
        "username": "Weierxunaidehua",
        "uid": null
      },
      "author_flair_text": null,
      "score": 1,
      "body": "<div class=\"wb-3\">一男一女赤身裸体面面相觑对着看手机真的黑色幽默</div>",
      "replies": 0,
      "created": "22-07-20"
    },
    {
      "kind": "t1",
      "id": "1932501",
      "author": {
        "username": "yuxiangrose",
        "uid": null
      },
      "author_flair_text": null,
      "score": 1,
      "body": "<div class=\"wb-3\">才260還想要啥？</div>",
      "replies": 0,
      "created": "22-07-20"
    },
    {
      "kind": "t1",
      "id": "1932359",
      "author": {
        "username": "HypothesisMaster",
        "uid": null
      },
      "author_flair_text": null,
      "score": 1,
      "body": "<div class=\"wb-3\">表演对白很王家卫</div>",
      "replies": 0,
      "created": "22-07-19"
    },
    {
      "kind": "t1",
      "id": "1932345",
      "author": {
        "username": "xijinping_xi",
        "uid": null
      },
      "author_flair_text": null,
      "score": 1,
      "body": "<div class=\"wb-3\">你的批真的很。。</div>",
      "replies": 0,
      "created": "22-07-19"
    },
    {
      "kind": "t1",
      "id": "1932310",
      "author": {
        "username": "xialan2016",
        "uid": null
      },
      "author_flair_text": null,
      "score": 1,
      "body": "<div class=\"wb-3\">两百六的逼真便宜</div>",
      "replies": 0,
      "created": "22-07-19"
    }
  ]
}