{
  "parent_id": "1924686",
  "reply_count": 6,
  "replies": [
    {
      "kind": "t1",
      "id": "1932853",
      "author": {
        "username": "Glum-Lychee6635",
        "uid": null
      },
      "author_flair_text": null,
      "score": 1,
      "body": "<div class=\"wb-3\">拆的不够，吱国至少拆四十块，鹅吱一百块</div>",
      "replies": 0,
      "created": "22-07-21"
    },
    {
      "kind": "t1",
      "id": "1932217",
      "author": {
        "username": "Key-Particular-5307",
        "uid": null
      },
      "author_flair_text": null,
      "score": 1,
      "body": "<div class=\"wb-3\">为啥不全占了</div>",
      "replies": 0,
      "created": "22-07-19"
    },
    {
      "kind": "t1",
      "id": "1932095",
      "author": {
        "username": "Unlucky-Box-1062",
        "uid": null
      },
      "author_flair_text": null,
      "score": 1,
      "body": "<div class=\"wb-3\">滿洲呢，我的滿洲呢</div>",
      "replies": 0,
      "created": "22-07-18"
    },
    {
      "kind": "t1",
      "id": "1932094",
      "author": {
        "username": "Designatedposition",
        "uid": null
      },
      "author_flair_text": null,
      "score": 1,
      "body": "<div class=\"wb-3\">标错了，洋人估计不知道北京具体位置在哪</div>",
      "replies": 0,
      "created": "22-07-18"
    },
    {
      "kind": "t1",
      "id": "1932086",
      "author": {
        "username": "Weierxunaidehua",
        "uid": null
      },
      "author_flair_text": null,
      "score": 1,
      "body": "<div class=\"wb-3\">什么航空母舰吧红迪分吧</div>",
      "replies": 0,
      "created": "22-07-18"
    },
    {
      "kind": "t1",
      "id": "1932078",
      "author": {
        "username": "xijinping_xi",
        "uid": null
      },
      "author_flair_text": null,
      "score": 1,
      "body": "<div class=\"wb-3\">台湾反攻大陆是吧</div>",
      "replies": 0,
      "created": "22-07-18"
    }
  ]
}