{
  "parent_id": "1924393",
  "reply_count": 2,
  "replies": [
    {
      "kind": "t1",
      "id": "1929056",
      "author": {
        "username": "Shazhi8964",
        "uid": null
      },
      "author_flair_text": null,
      "score": 1,
      "body": "<div class=\"wb-3\">什么电竞只需要回车键就能打</div>",
      "replies": 0,
      "created": "22-07-06"
    },
    {
      "kind": "t1",
      "id": "1929020",
      "author": {
        "username": "Abstract-neighbor",
        "uid": null
      },
      "author_flair_text": null,
      "score": 1,
      "body": "<div class=\"wb-3\">抽象派！</div>",
      "replies": 0,
      "created": "22-07-06"
    }
  ]
}