{
  "parent_id": "1924420",
  "reply_count": 6,
  "replies": [
    {
      "kind": "t1",
      "id": "1929325",
      "author": {
        "username": "apide_",
        "uid": null
      },
      "author_flair_text": null,
      "score": 1,
      "body": "<div class=\"wb-3\">确实我们都羡慕疯了。千万再别出来</div>",
      "replies": 0,
      "created": "22-07-08"
    },
    {
      "kind": "t1",
      "id": "1929316",
      "author": {
        "username": "noisyupstairs8964",
        "uid": null
      },
      "author_flair_text": null,
      "score": 1,
      "body": "<div class=\"wb-3\">可惜时薪不一定</div>",
      "replies": 0,
      "created": "22-07-08"
    },
    {
      "kind": "t1",
      "id": "1929258",
      "author": {
        "username": "-DETACHMENT-",
        "uid": null
      },
      "author_flair_text": null,
      "score": 1,
      "body": "<div class=\"wb-3\">7000人民币＞2000刀乐，陈平不等式的伟大变形</div>",
      "replies": 0,
      "created": "22-07-08"
    },
    {
      "kind": "t1",
      "id": "1929244",
      "author": {
        "username": "bihiki",
        "uid": null
      },
      "author_flair_text": null,
      "score": 1,
      "body": "<div class=\"wb-3\">习妈死了</div>",
      "replies": 0,
      "created": "22-07-07"
    },
    {
      "kind": "t1",
      "id": "1929234",
      "author": {
        "username": "polskamoze_",
        "uid": null
      },
      "author_flair_text": null,
      "score": 1,
      "body": "<div class=\"wb-3\">确实，马斯克已经羡慕疯了</div>",
      "replies": 0,
      "created": "22-07-07"
    },
    {
      "kind": "t1",
      "id": "1929230",
      "author": {
        "username": "DismalRegion8473",
        "uid": null
      },
      "author_flair_text": null,
      "score": 1,
      "body": "<div class=\"wb-3\">資本家肯定羨慕</div>",
      "replies": 0,
      "created": "22-07-07"
    }
  ]
}