{
  "parent_id": "1925541",
  "reply_count": 4,
  "replies": [
    {
      "kind": "t1",
      "id": "1942227",
      "author": {
        "username": "MundaneAssociation71",
        "uid": null
      },
      "author_flair_text": null,
      "score": 1,
      "body": "<div class=\"wb-3\">看过了</div>",
      "replies": 0,
      "created": "22-08-08"
    },
    {
      "kind": "t1",
      "id": "1942027",
      "author": {
        "username": "Arizona567",
        "uid": null
      },
      "author_flair_text": null,
      "score": 1,
      "body": "<div class=\"wb-3\">袜子脱下来套我牛子上</div>",
      "replies": 0,
      "created": "22-08-07"
    },
    {
      "kind": "t1",
      "id": "1942004",
      "author": {
        "username": "buggyass",
        "uid": null
      },
      "author_flair_text": null,
      "score": 1,
      "body": "<div class=\"wb-3\">白妹腿都抬起来了，小黄人还要搭凳子才能够得着😭</div>",
      "replies": 0,
      "created": "22-08-07"
    },
    {
      "kind": "t1",
      "id": "1941981",
      "author": {
        "username": "Efficient_Address634",
        "uid": null
      },
      "author_flair_text": null,
      "score": 1,
      "body": "<div class=\"wb-3\">🥵</div>",
      "replies": 0,
      "created": "22-08-07"
    }
  ]
}