{
  "parent_id": "1925270",
  "reply_count": 3,
  "replies": [
    {
      "kind": "t1",
      "id": "1939038",
      "author": {
        "username": "j092rtinv8h984h",
        "uid": null
      },
      "author_flair_text": null,
      "score": 1,
      "body": "<div class=\"wb-3\">营造正确的集体记忆中，少话！</div>",
      "replies": 0,
      "created": "22-08-04"
    },
    {
      "kind": "t1",
      "id": "1939035",
      "author": {
        "username": "doomofbanned",
        "uid": null
      },
      "author_flair_text": null,
      "score": 1,
      "body": "<div class=\"wb-3\">微博挂了</div>",
      "replies": 0,
      "created": "22-08-04"
    },
    {
      "kind": "t1",
      "id": "1939028",
      "author": {
        "username": "EasyExtent9474",
        "uid": null
      },
      "author_flair_text": null,
      "score": 1,
      "body": "<div class=\"wb-3\">其实只是我包包的拿手好戏---拔网线</div>",
      "replies": 0,
      "created": "22-08-04"
    }
  ]
}