{
  "parent_id": "1925218",
  "reply_count": 3,
  "replies": [
    {
      "kind": "t1",
      "id": "1938622",
      "author": {
        "username": "FreeHK_Now_Ray",
        "uid": null
      },
      "author_flair_text": null,
      "score": 1,
      "body": "<div class=\"wb-3\">可以啊， 給那韓國魚當一下人大委員長就好了， 馬上直接就能訪問台灣。</div>",
      "replies": 0,
      "created": "22-08-04"
    },
    {
      "kind": "t1",
      "id": "1938577",
      "author": {
        "username": "Independent-Judge-54",
        "uid": null
      },
      "author_flair_text": null,
      "score": 1,
      "body": "<div class=\"wb-3\">還挺好看</div>",
      "replies": 0,
      "created": "22-08-04"
    },
    {
      "kind": "t1",
      "id": "1938496",
      "author": {
        "username": "Zuomengne",
        "uid": null
      },
      "author_flair_text": null,
      "score": 1,
      "body": "<div class=\"wb-3\">起性欲了</div>",
      "replies": 0,
      "created": "22-08-04"
    }
  ]
}