{
  "parent_id": "1925727",
  "reply_count": 4,
  "replies": [
    {
      "kind": "t1",
      "id": "1944755",
      "author": {
        "username": "Xingping8964",
        "uid": null
      },
      "author_flair_text": null,
      "score": 1,
      "body": "<div class=\"wb-3\">无效的历史文件罢了</div>",
      "replies": 0,
      "created": "22-08-11"
    },
    {
      "kind": "t1",
      "id": "1944684",
      "author": {
        "username": "chinobuta",
        "uid": null
      },
      "author_flair_text": null,
      "score": 1,
      "body": "<div class=\"wb-3\">前面忘了，不共戴天</div>",
      "replies": 0,
      "created": "22-08-10"
    },
    {
      "kind": "t1",
      "id": "1944582",
      "author": {
        "username": "SeaRecognition5151",
        "uid": null
      },
      "author_flair_text": null,
      "score": 1,
      "body": "<div class=\"wb-3\">我九个评价中共</div>",
      "replies": 0,
      "created": "22-08-10"
    },
    {
      "kind": "t1",
      "id": "1944346",
      "author": {
        "username": "Hiroshi8964",
        "uid": null
      },
      "author_flair_text": null,
      "score": 1,
      "body": "<div class=\"wb-3\">好！</div>",
      "replies": 0,
      "created": "22-08-10"
    }
  ]
}