{
  "parent_id": "1925773",
  "reply_count": 3,
  "replies": [
    {
      "kind": "t1",
      "id": "1944967",
      "author": {
        "username": "Szzz2022",
        "uid": null
      },
      "author_flair_text": null,
      "score": 1,
      "body": "<div class=\"wb-3\">这下主动开辟第二战场了</div>",
      "replies": 0,
      "created": "22-08-11"
    },
    {
      "kind": "t1",
      "id": "1944891",
      "author": {
        "username": "ThauBa",
        "uid": null
      },
      "author_flair_text": null,
      "score": 1,
      "body": "<div class=\"wb-3\">严谨来说是日本EED，冲绳200海里，东シナ海到到菲律宾海那一带</div>",
      "replies": 0,
      "created": "22-08-11"
    },
    {
      "kind": "t1",
      "id": "1944868",
      "author": {
        "username": "Efficient_Address634",
        "uid": null
      },
      "author_flair_text": null,
      "score": 1,
      "body": "<div class=\"wb-3\">本來有一塊演習區域就劃在日本的專屬經濟海域 所以日本才抗議</div>",
      "replies": 0,
      "created": "22-08-11"
    }
  ]
}