{
  "parent_id": "1926468",
  "reply_count": 2,
  "replies": [
    {
      "kind": "t1",
      "id": "1953297",
      "author": {
        "username": "Green-Relationship22",
        "uid": null
      },
      "author_flair_text": null,
      "score": 1,
      "body": "<div class=\"wb-3\">艾特西</div>",
      "replies": 0,
      "created": "22-08-21"
    },
    {
      "kind": "t1",
      "id": "1953266",
      "author": {
        "username": "qianbbbbb",
        "uid": null
      },
      "author_flair_text": null,
      "score": 1,
      "body": "<div class=\"wb-3\">不如花山薰</div>",
      "replies": 0,
      "created": "22-08-21"
    }
  ]
}