{
  "parent_id": "1960823",
  "reply_count": 5,
  "replies": [
    {
      "kind": "t1",
      "id": "1967982",
      "author": {
        "username": "JAY_naomi",
        "uid": null
      },
      "author_flair_text": null,
      "score": 1,
      "body": "<div class=\"wb-3\">這下星際穿越了</div>",
      "replies": 0,
      "created": "22-08-30"
    },
    {
      "kind": "t1",
      "id": "1967954",
      "author": {
        "username": "seaangrybirds",
        "uid": null
      },
      "author_flair_text": null,
      "score": 1,
      "body": "<div class=\"wb-3\">什么保卫萝卜</div>",
      "replies": 0,
      "created": "22-08-30"
    },
    {
      "kind": "t1",
      "id": "1967902",
      "author": {
        "username": "Ilyinayo",
        "uid": null
      },
      "author_flair_text": null,
      "score": 1,
      "body": "<div class=\"wb-3\">什么反乌托邦</div>",
      "replies": 0,
      "created": "22-08-29"
    },
    {
      "kind": "t1",
      "id": "1967893",
      "author": {
        "username": "MousseDry1119",
        "uid": null
      },
      "author_flair_text": null,
      "score": 1,
      "body": "<div class=\"wb-3\">马戏团表演</div>",
      "replies": 0,
      "created": "22-08-29"
    },
    {
      "kind": "t1",
      "id": "1967882",
      "author": {
        "username": "Savings_Professor890",
        "uid": null
      },
      "author_flair_text": null,
      "score": 1,
      "body": "<div class=\"wb-3\">猪终于学会排队了，感动</div>",
      "replies": 0,
      "created": "22-08-29"
    }
  ]
}