{
  "parent_id": "1960810",
  "reply_count": 2,
  "replies": [
    {
      "kind": "t1",
      "id": "1967777",
      "author": {
        "username": "chasmalchemist",
        "uid": null
      },
      "author_flair_text": null,
      "score": 1,
      "body": "<div class=\"wb-3\">很奇怪吗？现在从西欧找一个40岁以下的年轻人有多难？生不出孩子自然就是种族替换，罗马人不生，日耳曼人生，马上南下成为真正罗马人</div>",
      "replies": 0,
      "created": "22-08-28"
    },
    {
      "kind": "t1",
      "id": "1967768",
      "author": {
        "username": "realTsarOfRussia",
        "uid": null
      },
      "author_flair_text": null,
      "score": 1,
      "body": "<div class=\"wb-3\">以前骂德法，现在看英国都被渗透成筛子了（我其实有个问题，港资算不算中国的？看到伦敦这么多地产，我想起来李嘉诚好像在英国投资过）</div>",
      "replies": 0,
      "created": "22-08-28"
    }
  ]
}