{
  "parent_id": "1960477",
  "reply_count": 4,
  "replies": [
    {
      "kind": "t1",
      "id": "1964775",
      "author": {
        "username": "jjking_Zigang-Liao",
        "uid": null
      },
      "author_flair_text": null,
      "score": 2,
      "body": "<div class=\"wb-3\">反了天了</div>",
      "replies": 0,
      "created": "22-07-31"
    },
    {
      "kind": "t1",
      "id": "1964803",
      "author": {
        "username": "Dd19411945",
        "uid": null
      },
      "author_flair_text": null,
      "score": 1,
      "body": "<div class=\"wb-3\">中華民國是中國大陸的合法政府</div>",
      "replies": 0,
      "created": "22-07-31"
    },
    {
      "kind": "t1",
      "id": "1964802",
      "author": {
        "username": "Key-Mud-6810",
        "uid": null
      },
      "author_flair_text": null,
      "score": 0,
      "body": "<div class=\"wb-3\">自罚三杯！</div>",
      "replies": 0,
      "created": "22-07-31"
    },
    {
      "kind": "t1",
      "id": "1964796",
      "author": {
        "username": "NewBella",
        "uid": null
      },
      "author_flair_text": null,
      "score": 0,
      "body": "<div class=\"wb-3\">真不好意思</div>",
      "replies": 0,
      "created": "22-07-31"
    }
  ]
}