{
  "parent_id": "1960025",
  "reply_count": 2,
  "replies": [
    {
      "kind": "t1",
      "id": "1960913",
      "author": {
        "username": "Zhizhiweizhizhi",
        "uid": null
      },
      "author_flair_text": null,
      "score": 1,
      "body": "<div class=\"wb-3\">应该是曹操是俄畜，孙权是乌克兰，曹操抢占了荆州还妄图拿下整个江东，结果废拉不堪的把脸都丢完了</div>",
      "replies": 0,
      "created": "22-06-09"
    },
    {
      "kind": "t1",
      "id": "1960908",
      "author": {
        "username": "Kure_Cucumber123",
        "uid": null
      },
      "author_flair_text": null,
      "score": 1,
      "body": "<div class=\"wb-3\">不知道是哪国，看校服似乎是新加坡风格的（这让我松了一口气）。</div>",
      "replies": 0,
      "created": "22-06-09"
    }
  ]
}