{
  "parent_id": "1968781",
  "reply_count": 5,
  "replies": [
    {
      "kind": "t1",
      "id": "1970883",
      "author": {
        "username": "michirinnn88",
        "uid": null
      },
      "author_flair_text": null,
      "score": 2,
      "body": "<div class=\"wb-3\">你给我回来</div>",
      "replies": 0,
      "created": "22-03-27"
    },
    {
      "kind": "t1",
      "id": "1970882",
      "author": {
        "username": "Kozure_Ookami",
        "uid": null
      },
      "author_flair_text": null,
      "score": 2,
      "body": "<div class=\"wb-3\">一直都是🦇人📺</div>",
      "replies": 0,
      "created": "22-03-27"
    },
    {
      "kind": "t1",
      "id": "1970935",
      "author": {
        "username": "sluttywhore420",
        "uid": null
      },
      "author_flair_text": null,
      "score": 1,
      "body": "<div class=\"wb-3\">开盒了</div>",
      "replies": 0,
      "created": "22-04-13"
    },
    {
      "kind": "t1",
      "id": "1970884",
      "author": {
        "username": "tzf1003",
        "uid": null
      },
      "author_flair_text": null,
      "score": 1,
      "body": "<div class=\"wb-3\">你给我回来😭</div>",
      "replies": 0,
      "created": "22-03-27"
    },
    {
      "kind": "t1",
      "id": "1970886",
      "author": {
        "username": "FishballJohnny",
        "uid": null
      },
      "author_flair_text": null,
      "score": 0,
      "body": "<div class=\"wb-3\">倭人这么喜欢碰瓷俺国时间方块</div>",
      "replies": 0,
      "created": "22-03-27"
    }
  ]
}