{
  "parent_id": "1969339",
  "reply_count": 7,
  "replies": [
    {
      "kind": "t1",
      "id": "1973982",
      "author": {
        "username": "yangjia1",
        "uid": null
      },
      "author_flair_text": null,
      "score": 1,
      "body": "<div class=\"wb-3\">这种白男在洼地怕不是要引起踩踏事件</div>",
      "replies": 0,
      "created": "22-08-11"
    },
    {
      "kind": "t1",
      "id": "1973962",
      "author": {
        "username": "btlbtl",
        "uid": null
      },
      "author_flair_text": null,
      "score": 1,
      "body": "<div class=\"wb-3\">长得帅真好</div>",
      "replies": 0,
      "created": "22-08-10"
    },
    {
      "kind": "t1",
      "id": "1973947",
      "author": {
        "username": "Independent-Gur5098",
        "uid": null
      },
      "author_flair_text": null,
      "score": 1,
      "body": "<div class=\"wb-3\">脑子会了但戴着眼镜的眯眯眼学不会</div>",
      "replies": 0,
      "created": "22-08-10"
    },
    {
      "kind": "t1",
      "id": "1973913",
      "author": {
        "username": "Darkword1987",
        "uid": null
      },
      "author_flair_text": null,
      "score": 1,
      "body": "<div class=\"wb-3\">我大概到0:01的進度，接下來畫面就在警局了</div>",
      "replies": 0,
      "created": "22-08-10"
    },
    {
      "kind": "t1",
      "id": "1973910",
      "author": {
        "username": "BIGisComing",
        "uid": null
      },
      "author_flair_text": null,
      "score": 1,
      "body": "<div class=\"wb-3\">小黄人往那一坐人家马上跑了</div>",
      "replies": 0,
      "created": "22-08-10"
    },
    {
      "kind": "t1",
      "id": "1973902",
      "author": {
        "username": "-Revisionist-",
        "uid": null
      },
      "author_flair_text": null,
      "score": 1,
      "body": "<div class=\"wb-3\">我可以❤️❤️❤️</div>",
      "replies": 0,
      "created": "22-08-10"
    },
    {
      "kind": "t1",
      "id": "1973901",
      "author": {
        "username": "Ethanryusaki557",
        "uid": null
      },
      "author_flair_text": null,
      "score": 1,
      "body": "<div class=\"wb-3\">白哥哥是这么帅，比碳水小黄人不知道高到哪里去了</div>",
      "replies": 0,
      "created": "22-08-10"
    }
  ]
}