{
  "parent_id": "1969688",
  "reply_count": 5,
  "replies": [
    {
      "kind": "t1",
      "id": "1976073",
      "author": {
        "username": "RealisticPatient1982",
        "uid": null
      },
      "author_flair_text": null,
      "score": 1,
      "body": "<div class=\"wb-3\">明显是古代跟现在不一样，现代人用歪了呗，“古代人造字用的本意是好的，都是现在人用歪了”（滑稽）</div>",
      "replies": 0,
      "created": "22-09-18"
    },
    {
      "kind": "t1",
      "id": "1976071",
      "author": {
        "username": "ZhiNaZhuZhu",
        "uid": null
      },
      "author_flair_text": null,
      "score": 1,
      "body": "<div class=\"wb-3\">嫖娼 妓 嫉妒 奸<br/>\n太贴切了，太带派了</div>",
      "replies": 0,
      "created": "22-09-18"
    },
    {
      "kind": "t1",
      "id": "1976065",
      "author": {
        "username": "FantasticPear3799",
        "uid": null
      },
      "author_flair_text": null,
      "score": 1,
      "body": "<div class=\"wb-3\">关键女性本来就是那么贱啊</div>",
      "replies": 0,
      "created": "22-09-18"
    },
    {
      "kind": "t1",
      "id": "1976035",
      "author": {
        "username": "Hiroshi8964",
        "uid": null
      },
      "author_flair_text": null,
      "score": 1,
      "body": "<div class=\"wb-3\">发明新语哈哈</div>",
      "replies": 0,
      "created": "22-09-18"
    },
    {
      "kind": "t1",
      "id": "1976030",
      "author": {
        "username": "George_the_Facetious",
        "uid": null
      },
      "author_flair_text": null,
      "score": 1,
      "body": "<div class=\"wb-3\">汉语是男人造的，建议另起炉灶再创语言</div>",
      "replies": 0,
      "created": "22-09-18"
    }
  ]
}