{
  "parent_id": "1969704",
  "reply_count": 3,
  "replies": [
    {
      "kind": "t1",
      "id": "1976154",
      "author": {
        "username": "henanpunk",
        "uid": null
      },
      "author_flair_text": null,
      "score": 1,
      "body": "<div class=\"wb-3\">雪飞炎海变清凉  <br/>\n此心安处是吾乡</div>",
      "replies": 0,
      "created": "22-09-21"
    },
    {
      "kind": "t1",
      "id": "1976142",
      "author": {
        "username": "Abstract-neighbor",
        "uid": null
      },
      "author_flair_text": null,
      "score": 1,
      "body": "<div class=\"wb-3\">好骂</div>",
      "replies": 0,
      "created": "22-09-20"
    },
    {
      "kind": "t1",
      "id": "1976136",
      "author": {
        "username": "Nervous-Secret7320",
        "uid": null
      },
      "author_flair_text": null,
      "score": 1,
      "body": "<div class=\"wb-3\">难绷</div>",
      "replies": 0,
      "created": "22-09-20"
    }
  ]
}