{
  "parent_id": "1970392",
  "reply_count": 2,
  "replies": [
    {
      "kind": "t1",
      "id": "1980054",
      "author": {
        "username": "ACigaretteaftSex",
        "uid": null
      },
      "author_flair_text": null,
      "score": 1,
      "body": "<div class=\"wb-3\">我原本以为集美都是知行合一励志屠光所有男人的有志之士。今天居然看见她们用“帅哥”这个词还对男人大献殷勤，我可以说是很震惊了。</div>",
      "replies": 0,
      "created": "23-01-04"
    },
    {
      "kind": "t1",
      "id": "1980052",
      "author": {
        "username": "punkinzhina",
        "uid": null
      },
      "author_flair_text": null,
      "score": 1,
      "body": "<div class=\"wb-3\">抠上了</div>",
      "replies": 0,
      "created": "23-01-03"
    }
  ]
}