{
  "parent_id": "1970212",
  "reply_count": 2,
  "replies": [
    {
      "kind": "t1",
      "id": "1979370",
      "author": {
        "username": "Ironsbowl",
        "uid": null
      },
      "author_flair_text": null,
      "score": 1,
      "body": "<div class=\"wb-3\">什么叫和自然世界共振？地球级震动棒？</div>",
      "replies": 0,
      "created": "22-12-05"
    },
    {
      "kind": "t1",
      "id": "1979177",
      "author": {
        "username": "Kuroneko_502",
        "uid": null
      },
      "author_flair_text": null,
      "score": 1,
      "body": "<div class=\"wb-3\">陳文茜這麼舔共都能看？雞美差不多得了</div>",
      "replies": 0,
      "created": "22-11-29"
    }
  ]
}