{
  "parent_id": "1970568",
  "reply_count": 4,
  "replies": [
    {
      "kind": "t1",
      "id": "1981088",
      "author": {
        "username": "Icy_Collar6640",
        "uid": null
      },
      "author_flair_text": null,
      "score": 1,
      "body": "<div class=\"wb-3\">臭织女别猥琐嘻嘻地在这下水道里翻屎来挽救你的寂寞夜晚了。累不累啊。</div>",
      "replies": 0,
      "created": "23-02-26"
    },
    {
      "kind": "t1",
      "id": "1981079",
      "author": {
        "username": "Icy_Collar6640",
        "uid": null
      },
      "author_flair_text": null,
      "score": 1,
      "body": "<div class=\"wb-3\">一个浪友不想在国内生小孩想带老婆润再生小孩的，但是岁静织女给自己安排了个目标一定要生小孩的。离婚了不还是织女带走彩礼吗？于是不生的时候就是耽误生育年龄补偿金了是吧。不管生不生横竖都是国男欠织女，有个逼有个子宫就高贵是吧？操你们妈的。</div>",
      "replies": 0,
      "created": "23-02-24"
    },
    {
      "kind": "t1",
      "id": "1981078",
      "author": {
        "username": "Certain-Engineering4",
        "uid": null
      },
      "author_flair_text": null,
      "score": 1,
      "body": "<div class=\"wb-3\">彩礼是买卖婚姻的遗迹，古代叫做“纳征”。不过现在相当于古代的买妾，买妾是真的按身价给钱，聘妻则一般是给礼物，意义上不是按照利益来的。</div>",
      "replies": 0,
      "created": "23-02-24"
    },
    {
      "kind": "t1",
      "id": "1981077",
      "author": {
        "username": "michirinnn88",
        "uid": null
      },
      "author_flair_text": null,
      "score": 1,
      "body": "<div class=\"wb-3\">子宫套子嘛。只能靠出售子宫才能活得下去的样子</div>",
      "replies": 0,
      "created": "23-02-24"
    }
  ]
}