{
  "parent_id": "1970067",
  "reply_count": 4,
  "replies": [
    {
      "kind": "t1",
      "id": "1978581",
      "author": {
        "username": "Nervous-Secret7320",
        "uid": null
      },
      "author_flair_text": null,
      "score": 1,
      "body": "<div class=\"wb-3\">原来商业婚姻市场价是二十万，这有啥风险吗，有无懂哥来说说？</div>",
      "replies": 0,
      "created": "22-11-16"
    },
    {
      "kind": "t1",
      "id": "1978444",
      "author": {
        "username": "yasheeeesh",
        "uid": null
      },
      "author_flair_text": null,
      "score": 1,
      "body": "<div class=\"wb-3\">织女真的坏中坏 典型的欺软怕硬 谄媚权贵鄙视平民 确实恶心</div>",
      "replies": 0,
      "created": "22-11-13"
    },
    {
      "kind": "t1",
      "id": "1978437",
      "author": {
        "username": "xiaomienvquan",
        "uid": null
      },
      "author_flair_text": null,
      "score": 1,
      "body": "<div class=\"wb-3\">双标一直是㜅妹们的基本操作和生活方式，比如她能偷拍你你不能偷拍她、她能养鱼渣你你不能出轨渣她之类的，女畎鸡妹一天不搞双标，占不到便宜就浑身难受</div>",
      "replies": 0,
      "created": "22-11-13"
    },
    {
      "kind": "t1",
      "id": "1978434",
      "author": {
        "username": "Physical_Painting200",
        "uid": null
      },
      "author_flair_text": null,
      "score": 1,
      "body": "<div class=\"wb-3\">嗯文尾还要炫耀一下自己是央企，不屑于润。</div>",
      "replies": 0,
      "created": "22-11-13"
    }
  ]
}