{
  "parent_id": "1981566",
  "reply_count": 8,
  "replies": [
    {
      "kind": "t1",
      "id": "1982545",
      "author": {
        "username": "Main_Awareness7163",
        "uid": null
      },
      "author_flair_text": null,
      "score": 1,
      "body": "<div class=\"wb-3\">说实话等你老了 支付宝这公司在不在都是问题</div>",
      "replies": 0,
      "created": "23-03-03"
    },
    {
      "kind": "t1",
      "id": "1982534",
      "author": {
        "username": "tank-GOD-deng",
        "uid": null
      },
      "author_flair_text": null,
      "score": 1,
      "body": "<div class=\"wb-3\">栓！</div>",
      "replies": 0,
      "created": "23-03-03"
    },
    {
      "kind": "t1",
      "id": "1982494",
      "author": {
        "username": "so02k",
        "uid": null
      },
      "author_flair_text": null,
      "score": 1,
      "body": "<div class=\"wb-3\">你不是在国外吗？</div>",
      "replies": 0,
      "created": "23-02-28"
    },
    {
      "kind": "t1",
      "id": "1982493",
      "author": {
        "username": "gaba6657",
        "uid": null
      },
      "author_flair_text": null,
      "score": 1,
      "body": "<div class=\"wb-3\">撸小贷整个几千几万，到手后换成美刀第二天就走线</div>",
      "replies": 0,
      "created": "23-02-28"
    },
    {
      "kind": "t1",
      "id": "1982492",
      "author": {
        "username": "shilloya",
        "uid": null
      },
      "author_flair_text": null,
      "score": 1,
      "body": "<div class=\"wb-3\">你這收入也太低了吧，我鄰居0.5公頃年收入也有100萬</div>",
      "replies": 0,
      "created": "23-02-28"
    },
    {
      "kind": "t1",
      "id": "1982489",
      "author": {
        "username": "Russsian27",
        "uid": null
      },
      "author_flair_text": null,
      "score": 1,
      "body": "<div class=\"wb-3\">你去58同城大兴安岭找个保安做，工资挺高</div>",
      "replies": 0,
      "created": "23-02-28"
    },
    {
      "kind": "t1",
      "id": "1982488",
      "author": {
        "username": "spiderhell1999",
        "uid": null
      },
      "author_flair_text": null,
      "score": 1,
      "body": "<div class=\"wb-3\">我觉得在<mark>支那</mark>买保险不如把这钱拿去改善伙食</div>",
      "replies": 0,
      "created": "23-02-28"
    },
    {
      "kind": "t1",
      "id": "1982487",
      "author": {
        "username": "Complete-Study674",
        "uid": null
      },
      "author_flair_text": null,
      "score": 1,
      "body": "<div class=\"wb-3\">种地还缺人吗</div>",
      "replies": 0,
      "created": "23-02-28"
    }
  ]
}