{
  "parent_id": "1981967",
  "reply_count": 7,
  "replies": [
    {
      "kind": "t1",
      "id": "1985384",
      "author": {
        "username": "Independent_Tip_3787",
        "uid": null
      },
      "author_flair_text": null,
      "score": 1,
      "body": "<div class=\"wb-3\">陳睿你整改了個雞巴毛啊</div>",
      "replies": 0,
      "created": "23-04-16"
    },
    {
      "kind": "t1",
      "id": "1985339",
      "author": {
        "username": "Civil-Alternative651",
        "uid": null
      },
      "author_flair_text": null,
      "score": 1,
      "body": "<div class=\"wb-3\">1985:好汉重生</div>",
      "replies": 0,
      "created": "23-04-16"
    },
    {
      "kind": "t1",
      "id": "1985291",
      "author": {
        "username": "Background-Drink9347",
        "uid": null
      },
      "author_flair_text": null,
      "score": 1,
      "body": "<div class=\"wb-3\">河南独立，唯一出路</div>",
      "replies": 0,
      "created": "23-04-15"
    },
    {
      "kind": "t1",
      "id": "1985289",
      "author": {
        "username": "kyxw234",
        "uid": null
      },
      "author_flair_text": null,
      "score": 1,
      "body": "<div class=\"wb-3\">荷兰滴，信阳滴，我是信阳姓吴滴，请问你是哪里滴</div>",
      "replies": 0,
      "created": "23-04-15"
    },
    {
      "kind": "t1",
      "id": "1985286",
      "author": {
        "username": "Used_Illustrator_610",
        "uid": null
      },
      "author_flair_text": null,
      "score": 1,
      "body": "<div class=\"wb-3\">幽默</div>",
      "replies": 0,
      "created": "23-04-15"
    },
    {
      "kind": "t1",
      "id": "1985244",
      "author": {
        "username": "ZH_Ray",
        "uid": null
      },
      "author_flair_text": null,
      "score": 1,
      "body": "<div class=\"wb-3\">AMERICAN SHENGDIYAGE</div>",
      "replies": 0,
      "created": "23-04-15"
    },
    {
      "kind": "t1",
      "id": "1985199",
      "author": {
        "username": "PANZER_04061989",
        "uid": null
      },
      "author_flair_text": null,
      "score": 1,
      "body": "<div class=\"wb-3\">愛德華茲 你在哪裡</div>",
      "replies": 0,
      "created": "23-04-15"
    }
  ]
}